poetry_zippy_plugin/__init__.py
poetry_zippy_plugin/plugin.py
poetry_zippy_plugin/zippy.py
poetry_zippy_plugin-0.1.0.dist-info/METADATA
poetry_zippy_plugin-0.1.0.dist-info/WHEEL
poetry_zippy_plugin-0.1.0.dist-info/entry_points.txt
poetry_zippy_plugin-0.1.0.dist-info/RECORD
