Metadata-Version: 2.3
Name: poetry-zippy-plugin
Version: 0.1.0
Summary: Poetry plugin to install dependencies to a target directory and create zip files for deploying to AWS Lambda
Author: Adam McKay
Author-email: adam@beepboop.digital
Requires-Python: >=3.10,<4.0
Classifier: Programming Language :: Python :: 3
Classifier: Programming Language :: Python :: 3.10
Classifier: Programming Language :: Python :: 3.11
Classifier: Programming Language :: Python :: 3.12
Classifier: Programming Language :: Python :: 3.13
Requires-Dist: poetry (>=2.0.0,<3.0.0)
